girder_import_tracker/__init__.py
girder_import_tracker/girder_worker_plugin.py
girder_import_tracker/models.py
girder_import_tracker/rest.py
girder_import_tracker/utils.py
girder_import_tracker/web_client/dist/girder-plugin-import-tracker.umd.cjs
girder_import_tracker/web_client/dist/style.css
girder_import_tracker-5.0.0a14.dev27.dist-info/METADATA
girder_import_tracker-5.0.0a14.dev27.dist-info/WHEEL
girder_import_tracker-5.0.0a14.dev27.dist-info/entry_points.txt
girder_import_tracker-5.0.0a14.dev27.dist-info/top_level.txt
girder_import_tracker-5.0.0a14.dev27.dist-info/RECORD
