Metadata-Version: 2.4
Name: girder-import-tracker
Version: 5.0.0a14.dev27
Summary: A Girder plugin for data import tracking
Home-page: https://github.com/girder/girder/tree/master/plugins/import_tracker
Author: Kitware, Inc.
Author-email: kitware@kitware.com
License: Apache 2.0
Keywords: girder-plugin,import_tracker
Classifier: Development Status :: 5 - Production/Stable
Classifier: Natural Language :: English
Classifier: Programming Language :: Python :: 3
Requires-Dist: girder-jobs>=3.0.3
Requires-Dist: girder>=3.1.23
Dynamic: author
Dynamic: author-email
Dynamic: classifier
Dynamic: description
Dynamic: description-content-type
Dynamic: home-page
Dynamic: keywords
Dynamic: license
Dynamic: requires-dist
Dynamic: summary
